Workbook

Sheet 収支（前期）
A1: 令和 年 黒鳥三番組収支会計報告書（前期）
A4: 月 | B4: 日 | C4: 歳入（円） | D4: 歳出（円） | E4: 摘要 | F4: 項目
A53: 前期合計 | C53: =SUM(C5:C52) -> 0 | D53: =SUM(D5:D52) -> 0

Sheet 収支（後期）
A1: 令和 年 黒鳥三番組収支会計報告書（後期）
A4: 月 | B4: 日 | C4: 歳入（円） | D4: 歳出（円） | E4: 摘要 | F4: 項目
A48: 前年度繰越金 | C48: =SUMIF('収支（前期）'!F:F,"前年度繰越金",'収支（前期）'!C:C)+SUMIF('収支（後期）'!F5:F47,"前年度繰越金",'収支（後期）'!C5:C47) -> 0
A49: 自治会積立金 | C49: =SUMIF('収支（前期）'!F:F,"自治会積立金",'収支（前期）'!C:C)+SUMIF('収支（後期）'!F5:F47,"自治会積立金",'収支（後期）'!C5:C47) -> 0
A50: 前期合計
A51: 後期合計 | C51: =SUM(C5:C47) -> 0 | D51: =SUM(D5:D47) -> 0
A52: 総合計 | C52: =SUM(C50:C51) -> 0 | D52: =SUM(D50:D51) -> 0
A53: 次年度繰越金 | E53: 次年へ繰越金

Sheet 集計
A1: 令和 年 黒鳥三番組 収支会計 月別集計表
A3: 【前期（1月〜6月）】
A4: 月 | B4: 収入合計（円） | C4: 支出合計（円） | D4: 差引（円）
A5: 1月 | B5: =SUMIF('収支（前期）'!A:A,1,'収支（前期）'!C:C) -> 0 | C5: =SUMIF('収支（前期）'!A:A,1,'収支（前期）'!D:D) -> 0 | D5: =B5-C5 -> 0
A6: 2月 | B6: =SUMIF('収支（前期）'!A:A,2,'収支（前期）'!C:C) -> 0 | C6: =SUMIF('収支（前期）'!A:A,2,'収支（前期）'!D:D) -> 0 | D6: =B6-C6 -> 0
A7: 3月 | B7: =SUMIF('収支（前期）'!A:A,3,'収支（前期）'!C:C) -> 0 | C7: =SUMIF('収支（前期）'!A:A,3,'収支（前期）'!D:D) -> 0 | D7: =B7-C7 -> 0
A8: 4月 | B8: =SUMIF('収支（前期）'!A:A,4,'収支（前期）'!C:C) -> 0 | C8: =SUMIF('収支（前期）'!A:A,4,'収支（前期）'!D:D) -> 0 | D8: =B8-C8 -> 0
A9: 5月 | B9: =SUMIF('収支（前期）'!A:A,5,'収支（前期）'!C:C) -> 0 | C9: =SUMIF('収支（前期）'!A:A,5,'収支（前期）'!D:D) -> 0 | D9: =B9-C9 -> 0
A10: 6月 | B10: =SUMIF('収支（前期）'!A:A,6,'収支（前期）'!C:C) -> 0 | C10: =SUMIF('収支（前期）'!A:A,6,'収支（前期）'!D:D) -> 0 | D10: =B10-C10 -> 0
A11: 前期合計 | B11: =SUM(B5:B10) -> 0 | C11: =SUM(C5:C10) -> 0 | D11: =B11-C11 -> 0
A13: 【後期（7月〜12月）】
A14: 月 | B14: 収入合計（円） | C14: 支出合計（円） | D14: 差引（円）
A15: 7月 | B15: =SUMIF('収支（後期）'!A:A,7,'収支（後期）'!C:C) -> 0 | C15: =SUMIF('収支（後期）'!A:A,7,'収支（後期）'!D:D) -> 0 | D15: =B15-C15 -> 0
A16: 8月 | B16: =SUMIF('収支（後期）'!A:A,8,'収支（後期）'!C:C) -> 0 | C16: =SUMIF('収支（後期）'!A:A,8,'収支（後期）'!D:D) -> 0 | D16: =B16-C16 -> 0
A17: 9月 | B17: =SUMIF('収支（後期）'!A:A,9,'収支（後期）'!C:C) -> 0 | C17: =SUMIF('収支（後期）'!A:A,9,'収支（後期）'!D:D) -> 0 | D17: =B17-C17 -> 0
A18: 10月 | B18: =SUMIF('収支（後期）'!A:A,10,'収支（後期）'!C:C) -> 0 | C18: =SUMIF('収支（後期）'!A:A,10,'収支（後期）'!D:D) -> 0 | D18: =B18-C18 -> 0
A19: 11月 | B19: =SUMIF('収支（後期）'!A:A,11,'収支（後期）'!C:C) -> 0 | C19: =SUMIF('収支（後期）'!A:A,11,'収支（後期）'!D:D) -> 0 | D19: =B19-C19 -> 0
A20: 12月 | B20: =SUMIF('収支（後期）'!A:A,12,'収支（後期）'!C:C) -> 0 | C20: =SUMIF('収支（後期）'!A:A,12,'収支（後期）'!D:D) -> 0 | D20: =B20-C20 -> 0
A21: 後期合計 | B21: =SUM(B15:B20) -> 0 | C21: =SUM(C15:C20) -> 0 | D21: =B21-C21 -> 0
A23: 年間合計 | B23: =B11+B21 -> 0 | C23: =C11+C21 -> 0 | D23: =B23-C23 -> 0

Sheet 決算書
A2: 令和 年 黒鳥三番組自治会 決算書
B4: 令和 年 | C4: 歳入決算額 | D4: ='収支（後期）'!C52 -> 0 | E4: 自 令和 年 1月 1日
B5: 令和 年 | C5: 歳出決算額 | D5: ='収支（後期）'!D52 -> 0 | E5: 至 令和 年 12月31日
C7: 前年度繰越金 | D7: ='収支（後期）'!C48 -> 0
B8: 歳入の部 | F8: 単位：円
B9: 項 目 | C9: 令和 年予算 | D9: 令和 年決算 | E9: 比較 | F9: 摘要
B10: 1.前年度繰越金 | D10: =D7 -> 0 | E10: =D10-C10 -> 0 | F10: 前年度繰越金
B11: 2.自治会費 | E11: =C11-D11 -> 0 | F11: 10,000円×26世帯
B12: 3.助成金 | E12: =C12-D12 -> 0 | F12: 事務委託料・電気料金等
B13: 4.会費 | E13: =C13-D13 -> 0 | F13: 新年会・運動会・川前普請
B14: 5.資源ごみ回収 | E14: =C14-D14 -> 0 | F14: 資源ごみ回収
B15: 6.手数料収入 | E15: =C15-D15 -> 0 | F15: 交通災害共済手数料
B16: 7.預金利息 | E16: =C16-D16 -> 0 | F16: 農協預金利息
B17: 8.自治会積立金 | D17: ='収支（後期）'!C49 -> 0 | E17: =C17-D17 -> 0 | F17: 令和1年より積立開始（2,000円×26世帯）
B18: 歳入合計 | C18: =SUM(C10:C17) -> 0 | D18: =SUM(D10:D17) -> 0 | E18: =SUM(E10:E17) -> 0
B19: 歳出の部
B20: 項 目 | C20: 令和 年予算 | D20: 令和 年決算 | E20: 比較 | F20: 摘要
B21: 1.新年会・慰労会費 | E21: =C21-D21 -> 0 | F21: 新年会・運動会・川前普請
B22: 2.各種会費 | E22: =C22-D22 -> 0 | F22: 小中学校後援会・団体会費等
B23: 3.協賛・助成金 | E23: =C23-D23 -> 0 | F23: 各種協賛・八幡宮御神酒代
B24: 4.協力金・募金 | E24: =C24-D24 -> 0 | F24: 赤い羽根・細末助け合い等
B25: 5.営繕・管理費 | E25: =C25-D25 -> 0 | F25: ゴミ置き場・除雪・電気料
B26: 6.慶弔・見舞金 | E26: =C26-D26 -> 0 | F26: 香典等
B27: 7.会議費 | E27: =C27-D27 -> 0 | F27: 役員会議費
B28: 8.予備・雑費 | E28: =C28-D28 -> 0 | F28: 事務用品・その他
B29: 歳入合計 | C29: =SUM(C21:C28) -> 0 | D29: =SUM(D21:D28) -> 0 | E29: =SUM(E21:E28) -> 0
B31: 令和 年 | C31: 歳入決算額 | D31: =D18 -> 0 | E31: 自 令和 年 1月 1日
B32: 令和 年 | C32: 歳出決算額 | D32: =D29 -> 0 | E32: 至 令和 年 12月31日
B33: 差し引き残高 | C33: 次年度繰越金 | D33: =D31-D32 -> 0 | E33: （令和 年へ繰り越し）
B35: 令和 年 月 日 黒鳥三番組自治会会計 江端 敏之
B36: 会計監査の結果、適正に処理されていたことを認めます
D38: 会計監査 | F38: 印

Sheet 予算書（案）
A2: 令和 年 黒鳥三番組自治会予算書（案）
B4: 令和 年 | C4: 歳入予算額 | E4: 自 令和 年 1月 1日
B5: 令和 年 | C5: 歳出予算額 | E5: 至 令和 年 12月31日
B7: 歳入の部 | F7: 単位：円
B8: 項 目 | C8: 令和 年予算 | D8: 令和 年決算 | E8: 比較 | F8: 摘要
B9: 1.前年度繰越金 | E9: =C9-D9 -> 0 | F9: 前年度繰越金
B10: 2.自治会費 | E10: =C10-D10 -> 0 | F10: 10,000円×26世帯
B11: 3.助成金 | E11: =C11-D11 -> 0 | F11: 事務委託料・電気料金等
B12: 4.会費 | E12: =C12-D12 -> 0 | F12: 新年会・運動会・川前普請
B13: 5.資源ごみ回収 | E13: =C13-D13 -> 0 | F13: 資源ごみ回収
B14: 6.手数料収入 | E14: =C14-D14 -> 0 | F14: 交通災害共済手数料
B15: 7.預金利息 | E15: =C15-D15 -> 0 | F15: 農協預金利息
B16: 8.自治会積立金 | E16: =C16-D16 -> 0 | F16: 令和1年より積立開始（2,000円×26世帯）
B17: 歳入合計 | C17: =SUM(C9:C16) -> 0 | D17: =SUM(D9:D16) -> 0 | E17: =SUM(E9:E16) -> 0
B18: 歳出の部
B19: 項 目 | C19: 令和 年予算 | D19: 令和 年決算 | E19: 比較 | F19: 摘要
B20: 1.新年会・慰労会費 | E20: =C20-D20 -> 0 | F20: 新年会・運動会・川前普請
B21: 2.各種会費 | E21: =C21-D21 -> 0 | F21: 小中学校後援会・団体会費等
B22: 3.協賛・助成金 | E22: =C22-D22 -> 0 | F22: 各種協賛・八幡宮御神酒代
B23: 4.協力金・募金 | E23: =C23-D23 -> 0 | F23: 赤い羽根・細末助け合い等
B24: 5.営繕・管理費 | E24: =C24-D24 -> 0 | F24: ゴミ置き場・除雪・電気料
B25: 6.慶弔・見舞金 | E25: =C25-D25 -> 0 | F25: 香典等
B26: 7.会議費 | E26: =C26-D26 -> 0 | F26: 役員会議費
B27: 8.予備・雑費 | E27: =C27-D27 -> 0 | F27: 事務用品・その他
B28: 歳入合計 | C28: =SUM(C20:C27) -> 0 | D28: =SUM(D20:D27) -> 0 | E28: =SUM(E20:E27) -> 0
